daxxhub/__init__.py
daxxhub/daxxhub.otf
daxxhub/error404
daxxhub-1.1.dist-info/METADATA
daxxhub-1.1.dist-info/WHEEL
daxxhub-1.1.dist-info/top_level.txt
daxxhub-1.1.dist-info/RECORD
