Metadata-Version: 2.1
Name: daxxhub
Version: 1.1
Summary: daxxhub Logo Generator
Home-page: https://github.com/daxxteam/daxxhub
Author: Mr Daxx
Author-email: mrdaxxteam@gmail.com
License: MIT
Download-URL: https://github.com/daxxteam/daxxhub/archive/0.1.tar.gz
Keywords: daxxhub,logo,generator
Platform: UNKNOWN
Classifier: Development Status :: 3 - Alpha
Classifier: Intended Audience :: Developers
Classifier: Topic :: Software Development :: Build Tools
Classifier: License :: OSI Approved :: MIT License
Classifier: Programming Language :: Python :: 3.8
Classifier: Programming Language :: Python :: 3.9
Requires-Dist: pillow
